{
    "$schema": "https://schema.management.azure.com/schemas/2019-04-01/deploymentTemplate.json#",
    "contentVersion": "1.0.0.0",
    "parameters": {
        "AddressSpace": {
            "type": "string"
        },
        "Subnet1-AddressSpace": {
            "type": "string"
        },
        "DNSServer": {
            "type": "string",
            "defaultValue": "168.63.129.16"
        }
    },
  "variables": {
    "vNetName": "[concat(resourceGroup().name, '-Net')]",
	  "SubnetName": "Subnet1"
  },
  "resources": [
    {
      "name": "[variables('vNetName')]",
      "type": "Microsoft.Network/virtualNetworks",
      "location": "[resourceGroup().location]",
      "apiVersion": "2019-11-01",
      "dependsOn": [],
      "properties": {
        "enableDdosProtection": false,
        "enableVmProtection": false,
        "addressSpace": {
          "addressPrefixes": [
            "[parameters('AddressSpace')]"
          ]
        },
        "dhcpOptions": {
          "dnsServers": [
            "[parameters('DNSServer')]"
          ]
        },
        "subnets": [
          {
            "name": "[variables('SubnetName')]",
            "properties": {
              "addressPrefix": "[parameters('Subnet1-AddressSpace')]"
            }
          }
        ]
      }
    }
  ]
}